python_scripts_eddielechtus/Arranging_Coins.py
python_scripts_eddielechtus/BFS.py
python_scripts_eddielechtus/BSF_Tree.py
python_scripts_eddielechtus/BSF_Tree_(Queue).py
python_scripts_eddielechtus/BST.py
python_scripts_eddielechtus/Bus.py
python_scripts_eddielechtus/Consecutive_Subsequences.py
python_scripts_eddielechtus/Dijkstra.py
python_scripts_eddielechtus/Djikstra_PrioorityQueue.py
python_scripts_eddielechtus/Flatten_Binary_Tree_to_Linked_List.py
python_scripts_eddielechtus/K-th_Symbol_in_Grammar.py
python_scripts_eddielechtus/Largest_Number_After_Mutating_Substring.py
python_scripts_eddielechtus/Largest_Submatrix_With_Rearrangements.py
python_scripts_eddielechtus/Pangram.py
python_scripts_eddielechtus/PersonStudent.py
python_scripts_eddielechtus/PriorotyQueue.py
python_scripts_eddielechtus/Reorder_Data_in_Log_Files.py
python_scripts_eddielechtus/Shortest_Completing_Word.py
python_scripts_eddielechtus/Smallest_Subsequence_of_Distinct_Characters.py
python_scripts_eddielechtus/Top_K_Frequent_Words.py
python_scripts_eddielechtus/Top_K_Frequent_Words_2.py
python_scripts_eddielechtus/Vehical.py
python_scripts_eddielechtus/Verifying_an_Alien_Dictionary.py
python_scripts_eddielechtus/__init__.py
python_scripts_eddielechtus/all_1_at_k.py
python_scripts_eddielechtus/all_1_at_k_places.py
python_scripts_eddielechtus/argparse_ex.py
python_scripts_eddielechtus/args.py
python_scripts_eddielechtus/arr_even_numbers.py
python_scripts_eddielechtus/array_equal_pairs.py
python_scripts_eddielechtus/asynco.py
python_scripts_eddielechtus/bankAccount.py
python_scripts_eddielechtus/binarySearch_rep.py
python_scripts_eddielechtus/binary_gap.py
python_scripts_eddielechtus/binary_search.py
python_scripts_eddielechtus/bubble_sort.py
python_scripts_eddielechtus/change_char_at_index.py
python_scripts_eddielechtus/clock_angle.py
python_scripts_eddielechtus/clock_angle_gfg.py
python_scripts_eddielechtus/closer_function_multiplication.py
python_scripts_eddielechtus/constructor.py
python_scripts_eddie_lechtus-0.0.1.dist-info/LICENSE
python_scripts_eddie_lechtus-0.0.1.dist-info/METADATA
python_scripts_eddie_lechtus-0.0.1.dist-info/WHEEL
python_scripts_eddie_lechtus-0.0.1.dist-info/top_level.txt
python_scripts_eddie_lechtus-0.0.1.dist-info/RECORD
