Metadata-Version: 2.1
Name: python-scripts-eddie-lechtus
Version: 0.0.1
Summary: Python scripts
Author-email: Eddie Lechtus <eddie_lechtus@gmail.com>
License: Copyright (c) 2018 The Python Packaging Authority        
Project-URL: Homepage, https://github.com/pypa/sampleproject
Project-URL: Bug Tracker, https://github.com/pypa/sampleproject/issues
Classifier: Programming Language :: Python :: 3
Classifier: License :: OSI Approved :: MIT License
Classifier: Operating System :: OS Independent
Requires-Python: >=3.7
License-File: LICENSE
